main.py
acfun_get-1.0.3.dist-info/METADATA
acfun_get-1.0.3.dist-info/WHEEL
acfun_get-1.0.3.dist-info/entry_points.txt
acfun_get-1.0.3.dist-info/top_level.txt
acfun_get-1.0.3.dist-info/RECORD
